vgscode/__init__.py
vgscode/sanitizers.py
vgscode/kazakhstan/__init__.py
vgscode/kazakhstan/bin.py
vgscode/kazakhstan/iin.py
vgscode-1.0.3.dist-info/METADATA
vgscode-1.0.3.dist-info/WHEEL
vgscode-1.0.3.dist-info/licenses/LICENSE
vgscode-1.0.3.dist-info/RECORD
