Metadata-Version: 2.3
Name: vgscode
Version: 1.0.3
Summary: Validate Generate Sanitize Code
Project-URL: Homepage, https://github.com/smvrnn/vgscode.py
Project-URL: Repository, https://github.com/smvrnn/vgscode.py.git
Author: Yerlan Yeraliyev
License: MIT License
License-File: LICENSE
Keywords: Kazakhstan,bin,generate,iin,validate
Classifier: Development Status :: 5 - Production/Stable
Classifier: License :: OSI Approved :: MIT License
Classifier: Operating System :: OS Independent
Classifier: Programming Language :: Python :: 3
Requires-Python: >=3.8
